ffm.so
fastFM/utils.py
fastFM/datasets.py
fastFM/mcmc.py
fastFM/validation.py
fastFM/sgd.py
fastFM/bpr.py
fastFM/als.py
fastFM/__init__.py
fastFM/base.py
fastFM-0.2.11.dist-info/DESCRIPTION.rst
fastFM-0.2.11.dist-info/METADATA
fastFM-0.2.11.dist-info/RECORD
fastFM-0.2.11.dist-info/WHEEL
fastFM-0.2.11.dist-info/metadata.json
fastFM-0.2.11.dist-info/top_level.txt
